protoc_gen_http_python/__init__.py
protoc_gen_http_python/http.py
protoc_gen_http_python/main.py
protoc_gen_http_python/template.py
protoc_gen_http_python/util.py
protoc_gen_http_python-0.0.3.dist-info/LICENSE
protoc_gen_http_python-0.0.3.dist-info/METADATA
protoc_gen_http_python-0.0.3.dist-info/WHEEL
protoc_gen_http_python-0.0.3.dist-info/entry_points.txt
protoc_gen_http_python-0.0.3.dist-info/top_level.txt
protoc_gen_http_python-0.0.3.dist-info/RECORD
